acorn_prng/src/acorn_prng.v
////////////////////////////////////////////////////////////////////////////////////////////
// ACORN (Additive Congruential Random Number) generator, a pseudo random number generator
// Inspired from this page: http://acorn.wikramaratna.org/ 
// Made by Zhenle Cao for the ZerotoASIC course
// Huge shoutout and appreciation to Steven Goldsmith for his invaluable assistance.
// March 2022, to be taped out on MPW5
// 16th order ACORN with modulus = 2^16, and easily scalable to higher modulos.
////////////////////////////////////////////////////////////////////////////////////////////

`default_nettype none
`timescale 1ns/1ps

module acorn_prng (

`ifdef USE_POWER_PINS
	inout vccd1,	// User area 1 1.8V power
	inout vssd1,	// User area 1 digital ground
`endif

    input clk,
    input reset,
    input wire load,
    input wire [1:0] select,
    input wire [11:0] gpio_seed,
    input wire [11:0] LA1_seed,
    output reg [11:0] out,
    output [12:0] io_oeb,
    output wire reset_out
);

assign io_oeb = 13'b0;

assign reset_out = reset;

reg [11:0] seed;

reg [11:0] r01;
reg [11:0] r02;
reg [11:0] r03;
reg [11:0] r04;
reg [11:0] r05;
reg [11:0] r06;
reg [11:0] r07;
reg [11:0] r08;
reg [11:0] r09;
reg [11:0] r010;
reg [11:0] r011;
reg [11:0] r012;
reg [11:0] r013;
reg [11:0] r014;
reg [11:0] r015;

reg [11:0] r10;
reg [11:0] r11;
reg [11:0] r12;
reg [11:0] r13;
reg [11:0] r14;
reg [11:0] r15;
reg [11:0] r16;
reg [11:0] r17;
reg [11:0] r18;
reg [11:0] r19;
reg [11:0] r110;
reg [11:0] r111;
reg [11:0] r112;
reg [11:0] r113;
reg [11:0] r114;
reg [11:0] r115;


reg [3:0] counter;



always @(posedge clk) begin


	if (reset) begin 

//everything to zero 

		counter <= 0;
		r01 <= 0;
		r02 <= 0;
		r03 <= 0;
		r04 <= 0;
		r05 <= 0;
		r06 <= 0;
		r07 <= 0;
		r08 <= 0;
		r09 <= 0;
		r010 <= 0;
		r011 <= 0;
		r012 <= 0;
		r013 <= 0;
		r014 <= 0;
		r015 <= 0;

		r11 <= 0;
		r12 <= 0;
		r13 <= 0;
		r14 <= 0;
		r15 <= 0;
		r16 <= 0;
		r17 <= 0;
		r18 <= 0;
		r19 <= 0;
		r110 <= 0;
		r111 <= 0;
		r112 <= 0;
		r113 <= 0;
		r114 <= 0;
		r115 <= 0;

		out <= 0;
		seed <= 0;
		

	end else 
	
	if (load) begin
	
	if(select == 2'b00)
	seed <= 12'b100000000001;
	
	if(select == 2'b11)
	seed <= 12'b111111111111;
	
	if(select == 2'b01)
	seed <= gpio_seed;
	
	if(select == 2'b10)
	seed <= LA1_seed;
	
	
	end else begin

	counter <= counter + 1;
	
	if(counter == 0)

	r11 <= r01+seed;
	
	if(counter == 1)

	r12 <= r02+r11;

	if(counter == 2)

	r13 <= r03+r12;

	if(counter == 3)
	r14 <= r04+r13;

	if(counter == 4)
	r15 <= r05+r14;

	if(counter == 5)
	r16 <= r06+r15;

	if(counter == 6)
	r17 <= r07+r16;

	if(counter == 7)
	r18 <= r08+r17;

	if(counter == 8)
	r19 <= r09+r18;

	if(counter == 9)
	r110 <= r010+r19;

	if(counter == 10)
	r111 <= r011+r110;

	if(counter == 11)
	r112 <= r012+r111;

	if(counter == 12)
	r113 <= r013+r112;

	if(counter == 13)
	r114 <= r014+r113;

	if(counter == 14)
	r115 <= r015+r114;

	if(counter == 15)

		out <= r115;

		r01 <= r11;
		r02 <= r12;
		r03 <= r13;
		r04 <= r14;
		r05 <= r15;
		r06 <= r16;
		r07 <= r17;
		r08 <= r18;
		r09 <= r19;
		r010 <= r110;
		r011 <= r111;
		r012 <= r112;
		r013 <= r113;
		r014 <= r114;
		r015 <= r115;
		


	end
end


endmodule

acorn_prng/acorn_prng.vcd
$date
	Mon Mar 21 01:07:35 2022
$end
$version
	Icarus Verilog
$end
$timescale
	1ps
$end
$scope module acorn_prng $end
$var wire 12 ! LA1_seed [11:0] $end
$var wire 1 " clk $end
$var wire 12 # gpio_seed [11:0] $end
$var wire 13 $ io_oeb [12:0] $end
$var wire 1 % load $end
$var wire 1 & reset $end
$var wire 1 ' reset_out $end
$var wire 2 ( select [1:0] $end
$var reg 4 ) counter [3:0] $end
$var reg 12 * out [11:0] $end
$var reg 12 + r01 [11:0] $end
$var reg 12 , r010 [11:0] $end
$var reg 12 - r011 [11:0] $end
$var reg 12 . r012 [11:0] $end
$var reg 12 / r013 [11:0] $end
$var reg 12 0 r014 [11:0] $end
$var reg 12 1 r015 [11:0] $end
$var reg 12 2 r02 [11:0] $end
$var reg 12 3 r03 [11:0] $end
$var reg 12 4 r04 [11:0] $end
$var reg 12 5 r05 [11:0] $end
$var reg 12 6 r06 [11:0] $end
$var reg 12 7 r07 [11:0] $end
$var reg 12 8 r08 [11:0] $end
$var reg 12 9 r09 [11:0] $end
$var reg 12 : r11 [11:0] $end
$var reg 12 ; r110 [11:0] $end
$var reg 12 < r111 [11:0] $end
$var reg 12 = r112 [11:0] $end
$var reg 12 > r113 [11:0] $end
$var reg 12 ? r114 [11:0] $end
$var reg 12 @ r115 [11:0] $end
$var reg 12 A r12 [11:0] $end
$var reg 12 B r13 [11:0] $end
$var reg 12 C r14 [11:0] $end
$var reg 12 D r15 [11:0] $end
$var reg 12 E r16 [11:0] $end
$var reg 12 F r17 [11:0] $end
$var reg 12 G r18 [11:0] $end
$var reg 12 H r19 [11:0] $end
$var reg 12 I seed [11:0] $end
$upscope $end
$enddefinitions $end
#0
$dumpvars
bx I
bx H
bx G
bx F
bx E
bx D
bx C
bx B
bx A
bx @
bx ?
bx >
bx =
bx <
bx ;
bx :
bx 9
bx 8
bx 7
bx 6
bx 5
bx 4
bx 3
bx 2
bx 1
bx 0
bx /
bx .
bx -
bx ,
bx +
bx *
bx )
bz (
1'
1&
z%
b0 $
bz #
0"
bz !
$end
#1000
b0 I
b0 *
b0 @
b0 ?
b0 >
b0 =
b0 <
b0 ;
b0 H
b0 G
b0 F
b0 E
b0 D
b0 C
b0 B
b0 A
b0 :
b0 1
b0 0
b0 /
b0 .
b0 -
b0 ,
b0 9
b0 8
b0 7
b0 6
b0 5
b0 4
b0 3
b0 2
b0 +
b0 )
1"
#2000
1%
0'
0&
b0 (
0"
#3000
b100000000001 I
1"
#4000
0%
0"
#5000
b100000000001 :
b1 )
1"
#6000
0"
#7000
b100000000001 +
b100000000001 A
b10 )
1"
#8000
0"
#9000
b100000000001 2
b100000000001 B
b11 )
1"
#10000
0"
#11000
b100000000001 3
b100000000001 C
b100 )
1"
#12000
0"
#13000
b100000000001 4
b100000000001 D
b101 )
1"
#14000
0"
#15000
b100000000001 5
b100000000001 E
b110 )
1"
#16000
0"
#17000
b100000000001 6
b100000000001 F
b111 )
1"
#18000
0"
#19000
b100000000001 7
b100000000001 G
b1000 )
1"
#20000
0"
#21000
b100000000001 8
b100000000001 H
b1001 )
1"
#22000
0"
#23000
b100000000001 9
b100000000001 ;
b1010 )
1"
#24000
0"
#25000
b100000000001 ,
b100000000001 <
b1011 )
1"
#26000
0"
#27000
b100000000001 -
b100000000001 =
b1100 )
1"
#28000
0"
#29000
b100000000001 .
b100000000001 >
b1101 )
1"
#30000
0"
#31000
b100000000001 /
b100000000001 ?
b1110 )
1"
#32000
0"
#33000
b100000000001 0
b100000000001 @
b1111 )
1"
#34000
0"
#35000
b100000000001 1
b100000000001 *
b0 )
1"
#36000
0"
#37000
b10 :
b1 )
1"
#38000
0"
#39000
b10 +
b100000000011 A
b10 )
1"
#40000
0"
#41000
b100000000011 2
b100 B
b11 )
1"
#42000
0"
#43000
b100 3
b100000000101 C
b100 )
1"
#44000
0"
#45000
b100000000101 4
b110 D
b101 )
1"
#46000
0"
#47000
b110 5
b100000000111 E
b110 )
1"
#48000
0"
#49000
b100000000111 6
b1000 F
b111 )
1"
#50000
0"
#51000
b1000 7
b100000001001 G
b1000 )
1"
#52000
0"
#53000
b100000001001 8
b1010 H
b1001 )
1"
#54000
0"
#55000
b1010 9
b100000001011 ;
b1010 )
1"
#56000
0"
#57000
b100000001011 ,
b1100 <
b1011 )
1"
#58000
0"
#59000
b1100 -
b100000001101 =
b1100 )
1"
#60000
0"
#61000
b100000001101 .
b1110 >
b1101 )
1"
#62000
0"
#63000
b1110 /
b100000001111 ?
b1110 )
1"
#64000
0"
#65000
b100000001111 0
b10000 @
b1111 )
1"
#66000
0"
#67000
b10000 1
b10000 *
b0 )
1"
#68000
0"
#69000
b100000000011 :
b1 )
1"
#70000
0"
#71000
b100000000011 +
b110 A
b10 )
1"
#72000
0"
#73000
b110 2
b1010 B
b11 )
1"
#74000
0"
#75000
b1010 3
b100000001111 C
b100 )
1"
#76000
0"
#77000
b100000001111 4
b100000010101 D
b101 )
1"
#78000
0"
#79000
b100000010101 5
b11100 E
b110 )
1"
#80000
0"
#81000
b11100 6
b100100 F
b111 )
1"
#82000
0"
#83000
b100100 7
b100000101101 G
b1000 )
1"
#84000
0"
#85000
b100000101101 8
b100000110111 H
b1001 )
1"
#86000
0"
#87000
b100000110111 9
b1000010 ;
b1010 )
1"
#88000
0"
#89000
b1000010 ,
b1001110 <
b1011 )
1"
#90000
0"
#91000
b1001110 -
b100001011011 =
b1100 )
1"
#92000
0"
#93000
b100001011011 .
b100001101001 >
b1101 )
1"
#94000
0"
#95000
b100001101001 /
b1111000 ?
b1110 )
1"
#96000
0"
#97000
b1111000 0
b10001000 @
b1111 )
1"
#98000
0"
#99000
b10001000 1
b10001000 *
b0 )
1"
#100000
0"
#101000
b100 :
b1 )
1"
#102000
0"
#103000
b100 +
b1010 A
b10 )
1"
#104000
0"
#105000
b1010 2
b10100 B
b11 )
1"
#106000
0"
#107000
b10100 3
b100000100011 C
b100 )
1"
#108000
0"
#109000
b100000100011 4
b111000 D
b101 )
1"
#110000
0"
#111000
b111000 5
b1010100 E
b110 )
1"
#112000
0"
#113000
b1010100 6
b1111000 F
b111 )
1"
#114000
0"
#115000
b1111000 7
b100010100101 G
b1000 )
1"
#116000
0"
#117000
b100010100101 8
b11011100 H
b1001 )
1"
#118000
0"
#119000
b11011100 9
b100011110 ;
b1010 )
1"
#120000
0"
#121000
b100011110 ,
b101101100 <
b1011 )
1"
#122000
0"
#123000
b101101100 -
b100111000111 =
b1100 )
1"
#124000
0"
#125000
b100111000111 .
b1000110000 >
b1101 )
1"
#126000
0"
#127000
b1000110000 /
b1010101000 ?
b1110 )
1"
#128000
0"
#129000
b1010101000 0
b1100110000 @
b1111 )
1"
#130000
0"
#131000
b1100110000 1
b1100110000 *
b0 )
1"
#132000
0"
#133000
b100000000101 :
b1 )
1"
#134000
0"
#135000
b100000000101 +
b100000001111 A
b10 )
1"
#136000
0"
#137000
b100000001111 2
b100000100011 B
b11 )
1"
#138000
0"
#139000
b100000100011 3
b1000110 C
b100 )
1"
#140000
0"
#141000
b1000110 4
b1111110 D
b101 )
1"
#142000
0"
#143000
b1111110 5
b11010010 E
b110 )
1"
#144000
0"
#145000
b11010010 6
b101001010 F
b111 )
1"
#146000
0"
#147000
b101001010 7
b100111101111 G
b1000 )
1"
#148000
0"
#149000
b100111101111 8
b101011001011 H
b1001 )
1"
#150000
0"
#151000
b101011001011 9
b101111101001 ;
b1010 )
1"
#152000
0"
#153000
b101111101001 ,
b110101010101 <
b1011 )
1"
#154000
0"
#155000
b110101010101 -
b11100011100 =
b1100 )
1"
#156000
0"
#157000
b11100011100 .
b100101001100 >
b1101 )
1"
#158000
0"
#159000
b100101001100 /
b101111110100 ?
b1110 )
1"
#160000
0"
#161000
b101111110100 0
b111100100100 @
b1111 )
1"
#162000
0"
#163000
b111100100100 1
b111100100100 *
b0 )
1"
#164000
0"
#165000
b110 :
b1 )
1"
#166000
0"
#167000
b110 +
b100000010101 A
b10 )
1"
#168000
0"
#169000
b100000010101 2
b111000 B
b11 )
1"
#170000
0"
#171000
b111000 3
b1111110 C
b100 )
1"
#172000
0"
#173000
b1111110 4
b11111100 D
b101 )
1"
#174000
0"
#175000
b11111100 5
b111001110 E
b110 )
1"
#176000
0"
#177000
b111001110 6
b1100011000 F
b111 )
1"
#178000
0"
#179000
b1100011000 7
b110100000111 G
b1000 )
1"
#180000
0"
#181000
b110100000111 8
b11111010010 H
b1001 )
1"
#182000
0"
#183000
b11111010010 9
b1110111011 ;
b1010 )
1"
#184000
0"
#185000
b1110111011 ,
b100010000 <
b1011 )
1"
#186000
0"
#187000
b100010000 -
b100000101100 =
b1100 )
1"
#188000
0"
#189000
b100000101100 .
b101111000 >
b1101 )
1"
#190000
0"
#191000
b101111000 /
b110101101100 ?
b1110 )
1"
#192000
0"
#193000
b110101101100 0
b110010010000 @
b1111 )
1"
#194000
0"
#195000
b110010010000 1
b110010010000 *
b0 )
1"
#196000
0"
#197000
b100000000111 :
b1 )
1"
#198000
0"
#199000
b100000000111 +
b11100 A
b10 )
1"
#200000
0"
#201000
b11100 2
b1010100 B
b11 )
1"
#202000
0"
#203000
b1010100 3
b11010010 C
b100 )
1"
#204000
1'
1&
0"
#205000
b0 I
b0 *
b0 @
b0 ?
b0 >
b0 =
b0 <
b0 ;
b0 H
b0 G
b0 F
b0 E
b0 D
b0 C
b0 B
b0 A
b0 :
b0 1
b0 0
b0 /
b0 .
b0 -
b0 ,
b0 9
b0 8
b0 7
b0 6
b0 5
b0 4
b0 3
b0 2
b0 +
b0 )
1"
#206000
1%
0'
0&
b11 (
0"
#207000
b111111111111 I
1"
#208000
0%
0"
#209000
b111111111111 :
b1 )
1"
#210000
0"
#211000
b111111111111 +
b111111111111 A
b10 )
1"
#212000
0"
#213000
b111111111111 2
b111111111111 B
b11 )
1"
#214000
0"
#215000
b111111111111 3
b111111111111 C
b100 )
1"
#216000
0"
#217000
b111111111111 4
b111111111111 D
b101 )
1"
#218000
0"
#219000
b111111111111 5
b111111111111 E
b110 )
1"
#220000
0"
#221000
b111111111111 6
b111111111111 F
b111 )
1"
#222000
0"
#223000
b111111111111 7
b111111111111 G
b1000 )
1"
#224000
0"
#225000
b111111111111 8
b111111111111 H
b1001 )
1"
#226000
0"
#227000
b111111111111 9
b111111111111 ;
b1010 )
1"
#228000
0"
#229000
b111111111111 ,
b111111111111 <
b1011 )
1"
#230000
0"
#231000
b111111111111 -
b111111111111 =
b1100 )
1"
#232000
0"
#233000
b111111111111 .
b111111111111 >
b1101 )
1"
#234000
0"
#235000
b111111111111 /
b111111111111 ?
b1110 )
1"
#236000
0"
#237000
b111111111111 0
b111111111111 @
b1111 )
1"
#238000
0"
#239000
b111111111111 1
b111111111111 *
b0 )
1"
#240000
0"
#241000
b111111111110 :
b1 )
1"
#242000
0"
#243000
b111111111110 +
b111111111101 A
b10 )
1"
#244000
0"
#245000
b111111111101 2
b111111111100 B
b11 )
1"
#246000
0"
#247000
b111111111100 3
b111111111011 C
b100 )
1"
#248000
0"
#249000
b111111111011 4
b111111111010 D
b101 )
1"
#250000
0"
#251000
b111111111010 5
b111111111001 E
b110 )
1"
#252000
0"
#253000
b111111111001 6
b111111111000 F
b111 )
1"
#254000
0"
#255000
b111111111000 7
b111111110111 G
b1000 )
1"
#256000
0"
#257000
b111111110111 8
b111111110110 H
b1001 )
1"
#258000
0"
#259000
b111111110110 9
b111111110101 ;
b1010 )
1"
#260000
0"
#261000
b111111110101 ,
b111111110100 <
b1011 )
1"
#262000
0"
#263000
b111111110100 -
b111111110011 =
b1100 )
1"
#264000
0"
#265000
b111111110011 .
b111111110010 >
b1101 )
1"
#266000
0"
#267000
b111111110010 /
b111111110001 ?
b1110 )
1"
#268000
0"
#269000
b111111110001 0
b111111110000 @
b1111 )
1"
#270000
0"
#271000
b111111110000 1
b111111110000 *
b0 )
1"
#272000
0"
#273000
b111111111101 :
b1 )
1"
#274000
0"
#275000
b111111111101 +
b111111111010 A
b10 )
1"
#276000
0"
#277000
b111111111010 2
b111111110110 B
b11 )
1"
#278000
0"
#279000
b111111110110 3
b111111110001 C
b100 )
1"
#280000
0"
#281000
b111111110001 4
b111111101011 D
b101 )
1"
#282000
0"
#283000
b111111101011 5
b111111100100 E
b110 )
1"
#284000
0"
#285000
b111111100100 6
b111111011100 F
b111 )
1"
#286000
0"
#287000
b111111011100 7
b111111010011 G
b1000 )
1"
#288000
0"
#289000
b111111010011 8
b111111001001 H
b1001 )
1"
#290000
0"
#291000
b111111001001 9
b111110111110 ;
b1010 )
1"
#292000
0"
#293000
b111110111110 ,
b111110110010 <
b1011 )
1"
#294000
0"
#295000
b111110110010 -
b111110100101 =
b1100 )
1"
#296000
0"
#297000
b111110100101 .
b111110010111 >
b1101 )
1"
#298000
0"
#299000
b111110010111 /
b111110001000 ?
b1110 )
1"
#300000
0"
#301000
b111110001000 0
b111101111000 @
b1111 )
1"
#302000
0"
#303000
b111101111000 1
b111101111000 *
b0 )
1"
#304000
0"
#305000
b111111111100 :
b1 )
1"
#306000
0"
#307000
b111111111100 +
b111111110110 A
b10 )
1"
#308000
0"
#309000
b111111110110 2
b111111101100 B
b11 )
1"
#310000
0"
#311000
b111111101100 3
b111111011101 C
b100 )
1"
#312000
0"
#313000
b111111011101 4
b111111001000 D
b101 )
1"
#314000
0"
#315000
b111111001000 5
b111110101100 E
b110 )
1"
#316000
0"
#317000
b111110101100 6
b111110001000 F
b111 )
1"
#318000
0"
#319000
b111110001000 7
b111101011011 G
b1000 )
1"
#320000
0"
#321000
b111101011011 8
b111100100100 H
b1001 )
1"
#322000
0"
#323000
b111100100100 9
b111011100010 ;
b1010 )
1"
#324000
0"
#325000
b111011100010 ,
b111010010100 <
b1011 )
1"
#326000
0"
#327000
b111010010100 -
b111000111001 =
b1100 )
1"
#328000
0"
#329000
b111000111001 .
b110111010000 >
b1101 )
1"
#330000
0"
#331000
b110111010000 /
b110101011000 ?
b1110 )
1"
#332000
0"
#333000
b110101011000 0
b110011010000 @
b1111 )
1"
#334000
0"
#335000
b110011010000 1
b110011010000 *
b0 )
1"
#336000
0"
#337000
b111111111011 :
b1 )
1"
#338000
0"
#339000
b111111111011 +
b111111110001 A
b10 )
1"
#340000
0"
#341000
b111111110001 2
b111111011101 B
b11 )
1"
#342000
0"
#343000
b111111011101 3
b111110111010 C
b100 )
1"
#344000
0"
#345000
b111110111010 4
b111110000010 D
b101 )
1"
#346000
0"
#347000
b111110000010 5
b111100101110 E
b110 )
1"
#348000
0"
#349000
b111100101110 6
b111010110110 F
b111 )
1"
#350000
0"
#351000
b111010110110 7
b111000010001 G
b1000 )
1"
#352000
0"
#353000
b111000010001 8
b110100110101 H
b1001 )
1"
#354000
0"
#355000
b110100110101 9
b110000010111 ;
b1010 )
1"
#356000
0"
#357000
b110000010111 ,
b101010101011 <
b1011 )
1"
#358000
0"
#359000
b101010101011 -
b100011100100 =
b1100 )
1"
#360000
0"
#361000
b100011100100 .
b11010110100 >
b1101 )
1"
#362000
0"
#363000
b11010110100 /
b10000001100 ?
b1110 )
1"
#364000
0"
#365000
b10000001100 0
b11011100 @
b1111 )
1"
#366000
0"
#367000
b11011100 1
b11011100 *
b0 )
1"
#368000
0"
#369000
b111111111010 :
b1 )
1"
#370000
0"
#371000
b111111111010 +
b111111101011 A
b10 )
1"
#372000
0"
#373000
b111111101011 2
b111111001000 B
b11 )
1"
#374000
0"
#375000
b111111001000 3
b111110000010 C
b100 )
1"
#376000
0"
#377000
b111110000010 4
b111100000100 D
b101 )
1"
#378000
0"
#379000
b111100000100 5
b111000110010 E
b110 )
1"
#380000
0"
#381000
b111000110010 6
b110011101000 F
b111 )
1"
#382000
0"
#383000
b110011101000 7
b101011111001 G
b1000 )
1"
#384000
0"
#385000
b101011111001 8
b100000101110 H
b1001 )
1"
#386000
0"
#387000
b100000101110 9
b10001000101 ;
b1010 )
1"
#388000
0"
#389000
b10001000101 ,
b111011110000 <
b1011 )
1"
#390000
0"
#391000
b111011110000 -
b11111010100 =
b1100 )
1"
#392000
0"
#393000
b11111010100 .
b111010001000 >
b1101 )
1"
#394000
0"
#395000
b111010001000 /
b1010010100 ?
b1110 )
1"
#396000
0"
#397000
b1010010100 0
b1101110000 @
b1111 )
1"
#398000
0"
#399000
b1101110000 1
b1101110000 *
b0 )
1"
#400000
0"
#401000
b111111111001 :
b1 )
1"
#402000
0"
#403000
b111111111001 +
b111111100100 A
b10 )
1"
#404000
0"
#405000
b111111100100 2
b111110101100 B
b11 )
1"
#406000
0"
#407000
b111110101100 3
b111100101110 C
b100 )
1"
